gemtest/__init__.py
gemtest/conftest.py
gemtest/decorator.py
gemtest/generator.py
gemtest/generators/__init__.py
gemtest/generators/randfloat.py
gemtest/generators/randint.py
gemtest/logger.py
gemtest/metamorphic_error.py
gemtest/metamorphic_relation.py
gemtest/metamorphic_test_case.py
gemtest/metamorphic_test_suite.py
gemtest/register.py
gemtest/relations/__init__.py
gemtest/relations/approximately.py
gemtest/relations/or_.py
gemtest/relations/simple.py
gemtest/report/__init__.py
gemtest/report/css/report.css
gemtest/report/data_exporter.py
gemtest/report/database_handler.py
gemtest/report/execution_report.py
gemtest/report/js/report.js
gemtest/report/report_handler.py
gemtest/report/string_generator.py
gemtest/report/visualizer.py
gemtest/testcase_queue.py
gemtest/testing_strategy.py
gemtest/types.py
gemtest/utils/__init__.py
gemtest/utils/data_loaders.py
gemtest/utils/sut_loader.py
gemtest/utils/wrong_skip_method_used.py
gemtest-1.0.1.dist-info/LICENSE
gemtest-1.0.1.dist-info/METADATA
gemtest-1.0.1.dist-info/WHEEL
gemtest-1.0.1.dist-info/entry_points.txt
gemtest-1.0.1.dist-info/RECORD
