Metadata-Version: 2.3
Name: gemtest
Version: 1.0.1
Summary: gemtest: a general metamorphic testing framework with pytest
License: MIT
Keywords: metamorphic testing,test,framework
Author: Simon Speth
Author-email: simon.speth@tum.de
Maintainer: Simon Speth
Maintainer-email: simon.speth@tum.de
Requires-Python: >=3.8,<3.14
Classifier: Development Status :: 5 - Production/Stable
Classifier: Framework :: Pytest
Classifier: Intended Audience :: Developers
Classifier: Intended Audience :: Science/Research
Classifier: License :: OSI Approved :: MIT License
Classifier: Natural Language :: English
Classifier: Operating System :: MacOS
Classifier: Operating System :: Microsoft :: Windows
Classifier: Operating System :: POSIX :: Linux
Classifier: Programming Language :: Python
Classifier: Programming Language :: Python :: 3
Classifier: Programming Language :: Python :: 3.8
Classifier: Programming Language :: Python :: 3.9
Classifier: Programming Language :: Python :: 3.10
Classifier: Programming Language :: Python :: 3.11
Classifier: Programming Language :: Python :: 3.12
Classifier: Programming Language :: Python :: 3.13
Classifier: Programming Language :: Python :: 3 :: Only
Classifier: Topic :: Software Development :: Libraries
Classifier: Topic :: Software Development :: Testing
Classifier: Topic :: Utilities
Requires-Dist: hypothesis (>=6.49.1,<7.0.0)
Requires-Dist: importlib-resources (<6.5.0) ; python_version == "3.8"
Requires-Dist: importlib-resources (>=6.5.0,<7.0.0) ; python_version == "3.9"
Requires-Dist: matplotlib (>=3.5.2,<4.0.0) ; python_version >= "3.8" and python_version < "3.12"
Requires-Dist: matplotlib (>=3.8.0,<4.0.0) ; python_version >= "3.12" and python_version < "3.14"
Requires-Dist: numpy (>=1.23.0,<2.0.0) ; python_version >= "3.8" and python_version < "3.12"
Requires-Dist: numpy (>=2.0.0,<3.0.0) ; python_version >= "3.12" and python_version < "3.14"
Requires-Dist: opencv-python-headless (>=4.7.0.0,<5.0.0.0)
Requires-Dist: pytest (>=7.1.2,<9.0.0)
Requires-Dist: pytest-html (>=3.1.1,<4.0.0)
Requires-Dist: pytest-xdist (>=3.2.1,<4.0.0)
Requires-Dist: typing_extensions (>=4.12.2,<5.0.0)
Requires-Dist: wrapt (>=1.14.1,<2.0.0)
Project-URL: Repository, https://github.com/tum-i4/gemtest
